qz_doudizhu/__init__.py
qz_doudizhu/qz_doudizhu.py
qz_doudizhu-1.0.1.dist-info/METADATA
qz_doudizhu-1.0.1.dist-info/WHEEL
qz_doudizhu-1.0.1.dist-info/licenses/LICENSE
qz_doudizhu-1.0.1.dist-info/RECORD
